{
    "match": {
        "win": 25.0,
        "loss": -50.0,
        "draw": -12.5
    },
    "turn": {
        "step_penalty": -0.05
    },
    "performance": {
        "score_scale": 0.1,
        "chain_bonus_scale": 0.1
    },
    "board": {
        "puyo_count_penalty": -0.001,
        "connectivity_bonus": 0.05,
        "isolated_puyo_penalty": -0.02,
        "death_col_height_penalty": -0.5,
        "color_diversity_reward": 0.02,
        "buried_puyo_penalty": -0.1,
        "ojama_drop_penalty": -0.2,
        "potential_chain_bonus_scale": 0.3
    },
    "opponent": {
        "field_pressure_reward": 0.01,
        "connectivity_penalty": -0.02,
        "ojama_diff_scale": 0.01,
        "initiative_bonus": 1.5
    }
}